pyback/__init__.py
pyback/_version.py
pyback/strategy.py
tests/__init__.py
tests/unit/__init__.py
tests/unit/test_strategy.py
pyback-0.0.2.dist-info/LICENSE
pyback-0.0.2.dist-info/METADATA
pyback-0.0.2.dist-info/WHEEL
pyback-0.0.2.dist-info/top_level.txt
pyback-0.0.2.dist-info/RECORD
